swatoutpy/__init__.py
swatoutpy/reader.py
swatoutpy/utils.py
swatoutpy-0.1.2.dist-info/METADATA
swatoutpy-0.1.2.dist-info/WHEEL
swatoutpy-0.1.2.dist-info/top_level.txt
swatoutpy-0.1.2.dist-info/RECORD
