Metadata-Version: 2.4
Name: swatoutpy
Version: 0.1.2
Summary: A Python package to read SWAT model output files (.rch, .sub, .hru)
Author-email: Gokhan Cuceloglu <cuceloglugokhan@gmail.com>
License-Expression: MIT
Project-URL: Homepage, https://github.com/gokhancuceloglu/swatoutpy
Project-URL: Source, https://github.com/gokhancuceloglu/swatoutpy
Requires-Python: >=3.7
Requires-Dist: pandas
